goal/__init__.py
goal/__main__.py
goal/cli.py
goal/commit_generator.py
goal/config.py
goal/deep_analyzer.py
goal/enhanced_summary.py
goal/formatter.py
goal/smart_commit.py
goal-2.1.25.dist-info/licenses/LICENSE
goal-2.1.25.dist-info/METADATA
goal-2.1.25.dist-info/WHEEL
goal-2.1.25.dist-info/entry_points.txt
goal-2.1.25.dist-info/top_level.txt
goal-2.1.25.dist-info/RECORD
