Metadata-Version: 2.4
Name: goal
Version: 2.1.25
Summary: Automated git push with smart commit messages, changelog updates, and version tagging
Author-email: wronai <wronai@example.com>
License: Apache-2.0
Project-URL: Homepage, https://github.com/wronai/goal
Project-URL: Repository, https://github.com/wronai/goal
Project-URL: Issues, https://github.com/wronai/goal/issues
Keywords: git,automation,commit,changelog,versioning,cli
Classifier: Development Status :: 4 - Beta
Classifier: Environment :: Console
Classifier: Intended Audience :: Developers
Classifier: License :: OSI Approved :: Apache Software License
Classifier: Operating System :: OS Independent
Classifier: Programming Language :: Python :: 3
Classifier: Programming Language :: Python :: 3.8
Classifier: Programming Language :: Python :: 3.9
Classifier: Programming Language :: Python :: 3.10
Classifier: Programming Language :: Python :: 3.11
Classifier: Programming Language :: Python :: 3.12
Classifier: Topic :: Software Development :: Version Control :: Git
Requires-Python: >=3.8
License-File: LICENSE
Requires-Dist: click>=8.0.0
Requires-Dist: PyYAML>=6.0
Provides-Extra: dev
Requires-Dist: pytest>=7.0.0; extra == "dev"
Requires-Dist: build; extra == "dev"
Requires-Dist: twine; extra == "dev"
Dynamic: license-file
